woid/__init__.py
woid/help.py
woid/log.py
woid/main.py
woid/py.typed
woid/version.py
woid/workspace.py
woid-0.1.dist-info/METADATA
woid-0.1.dist-info/WHEEL
woid-0.1.dist-info/entry_points.txt
woid-0.1.dist-info/licenses/LICENSE.md
woid-0.1.dist-info/RECORD
